cnd_cr/VERSION
cnd_cr/__init__.py
cnd_cr/__version__.py
cnd_cr/cr.py
cnd_cr-0.2.0.dist-info/METADATA
cnd_cr-0.2.0.dist-info/WHEEL
cnd_cr-0.2.0.dist-info/top_level.txt
cnd_cr-0.2.0.dist-info/RECORD
