Metadata-Version: 2.1
Name: cnd-cr
Version: 0.2.0
Summary: Base for vro Custom Resource
Home-page: https://gitlab.com/changendevops/cloudtools/cnd-cr.git
Author: Denis FABIEN
Author-email: denis.fabien@changendevops.com
License: MIT/X11
Project-URL: Documentation, https://changendevops.com
Project-URL: Source, https://gitlab.com/changendevops/cloudtools/cnd-cr.git
Classifier: License :: OSI Approved :: MIT License
Classifier: Operating System :: OS Independent
Requires-Dist: cndprint
Requires-Dist: pyyaml
Requires-Dist: requests
Requires-Dist: cndIo
Requires-Dist: yamale
